myxagent-0.2.32.dist-info/licenses/LICENSE
xagent/__init__.py
xagent/__version__.py
xagent/components/__init__.py
xagent/components/memory/__init__.py
xagent/components/memory/base_memory.py
xagent/components/memory/local_memory.py
xagent/components/memory/upstash_memory.py
xagent/components/memory/utils/__init__.py
xagent/components/memory/utils/llm_service.py
xagent/components/memory/utils/memory_config.py
xagent/components/memory/utils/messages_for_memory.py
xagent/components/message/__init__.py
xagent/components/message/base_messages.py
xagent/components/message/local_messages.py
xagent/components/message/redis_messages.py
xagent/core/__init__.py
xagent/core/agent.py
xagent/interfaces/__init__.py
xagent/interfaces/base.py
xagent/interfaces/cli.py
xagent/interfaces/server.py
xagent/interfaces/web.py
xagent/interfaces/web_launcher.py
xagent/multi/__init__.py
xagent/multi/swarm.py
xagent/multi/workflow.py
xagent/schemas/__init__.py
xagent/schemas/memory.py
xagent/schemas/message.py
xagent/tools/__init__.py
xagent/tools/openai_tool.py
xagent/utils/__init__.py
xagent/utils/image_upload.py
xagent/utils/mcp_convertor.py
xagent/utils/tool_decorator.py
xagent/utils/workflow_dsl.py
myxagent-0.2.32.dist-info/METADATA
myxagent-0.2.32.dist-info/WHEEL
myxagent-0.2.32.dist-info/entry_points.txt
myxagent-0.2.32.dist-info/top_level.txt
myxagent-0.2.32.dist-info/RECORD
