Metadata-Version: 2.4
Name: myxagent
Version: 0.2.32
Summary: Multi-Modal AI Agent System
Author-email: ZJun <zhangjun310@live.com>
License: MIT
Project-URL: Repository, https://github.com/ZJCODE/xagent
Project-URL: Issues, https://github.com/ZJCODE/xagent/issues
Project-URL: Homepage, https://github.com/ZJCODE/xagent#readme
Keywords: ai,agent,openai,chatbot,async
Classifier: Development Status :: 4 - Beta
Classifier: Intended Audience :: Developers
Classifier: License :: OSI Approved :: MIT License
Classifier: Topic :: Scientific/Engineering :: Artificial Intelligence
Classifier: Programming Language :: Python :: 3.10
Classifier: Programming Language :: Python :: 3.11
Classifier: Programming Language :: Python :: 3.12
Requires-Python: >=3.10
License-File: LICENSE
Requires-Dist: fastapi>=0.116.1
Requires-Dist: pydantic>=2.11.7
Requires-Dist: uvicorn>=0.35.0
Requires-Dist: openai>=1.98.0
Requires-Dist: fastmcp>=2.10.6
Requires-Dist: langfuse>=3.2.1
Requires-Dist: httpx>=0.28.1
Requires-Dist: requests>=2.32.0
Requires-Dist: redis>=6.2.0
Requires-Dist: chromadb>=1.0.20
Requires-Dist: upstash_vector>=0.8.0
Requires-Dist: boto3>=1.39.17
Requires-Dist: streamlit>=1.47.1
Requires-Dist: python-dotenv>=1.1.1
Requires-Dist: pyyaml>=6.0.2
Requires-Dist: tenacity>=9.1.2
Requires-Dist: watchdog>=6.0.0
Dynamic: license-file
